flareio/__init__.py
flareio/api_client.py
flareio/exceptions.py
flareio/py.typed
flareio/version.py
flareio-1.1.0.dist-info/LICENSE
flareio-1.1.0.dist-info/METADATA
flareio-1.1.0.dist-info/WHEEL
flareio-1.1.0.dist-info/RECORD
