Metadata-Version: 2.1
Name: flareio
Version: 1.1.0
Summary: Python SDK for the flare.io API.
Home-page: https://github.com/Flared/python-flareio
License: MIT
Keywords: flare,sdk
Author: Alexandre Viau
Author-email: alexandre.viau@flare.io
Requires-Python: >=3.8
Classifier: Intended Audience :: Developers
Classifier: Intended Audience :: Information Technology
Classifier: License :: OSI Approved :: MIT License
Classifier: Operating System :: POSIX :: Linux
Classifier: Programming Language :: Python :: 3
Classifier: Programming Language :: Python :: 3.8
Classifier: Programming Language :: Python :: 3.9
Classifier: Programming Language :: Python :: 3.10
Classifier: Programming Language :: Python :: 3.11
Classifier: Programming Language :: Python :: 3.12
Classifier: Topic :: Software Development :: Libraries :: Application Frameworks
Requires-Dist: requests (>=2)
Project-URL: Repository, https://github.com/Flared/python-flareio
